huskypo/__init__.py
huskypo/by.py
huskypo/config.py
huskypo/decorator.py
huskypo/ec_extension.py
huskypo/element.py
huskypo/elements.py
huskypo/logconfig.py
huskypo/logstack.py
huskypo/page.py
huskypo/types.py
huskypo/version.py
huskypo-1.4.2.dist-info/LICENSE
huskypo-1.4.2.dist-info/METADATA
huskypo-1.4.2.dist-info/WHEEL
huskypo-1.4.2.dist-info/top_level.txt
huskypo-1.4.2.dist-info/RECORD
